[
  //소대 유닛
  {
    "name": "Great War Infantry",
		"unitType": "Infantry",
		"movement": 2,
		"strength": 10,
		"cost": 490,
		"requiredTech": "Dynamite",
		"attackSound": "shot",
	    "uniques": ["[+500]% Strength <vs [MachineGun] units> <when attacking>", "[+500]% Strength <vs [canon] units> <when attacking>"]
	},
  {
		"name": "Infantry",//중대
		"unitType": "Infantry",
		"movement": 1,
		"strength": 35,
		"cost": 1700,
		"requiredTech": "Dynamite",
	    "requiredResource": "Horses:2",
		"attackSound": "shot",
	    "uniques": ["[+500]% Strength <vs [canon] units> <when attacking>", "[+500]% Strength <vs [MachineGun] units> <when attacking>"]
	},
  	{
		"name": "Machine Gun",//경기
		"unitType": "MachineGun",
		"range": 1,
		"movement": 2,
		"strength": 75,
		"rangedStrength": 4,
		"cost": 200,
		"requiredTech": "Dynamite",
		"attackSound": "machinegun"
		// Upgrades to Bazooka in BNW
	},
  {
        "name": "Gatling Gun",//기
		"unitType": "MachineGun",
		"range": 2,
		"movement": 1,
	    "movementCooldown":1,
		"strength": 75,
		"rangedStrength": 5,
	    "requiredResource": "Iron",
		"cost": 285,
		"requiredTech": "Dynamite",
		"attackSound": "machinegun"
	},
  {
		"name": "Anti-Aircraft Gun",//중기
		"unitType": "MachineGun",
		"movement": 1,
	    "movementCooldown":1,
		"strength": 80,
	    "rangedStrength": 8,
	    "Range": 3,
		"cost": 515,
	    "requiredResource": "Iron, Aluminum",
		"requiredTech": "Dynamite",
		"attackSound": "machinegun"
	},
{
		"name": "Minuteman",//전차형 경기
		"unitType": "MachineGun",
		"movement": 3,
		"strength": 50,
	    "rangedStrength": 4,
	    "Range": 1,
		"cost": 285,
	    "requiredResource": "Horses",
		"requiredTech": "Dynamite",
		"attackSound": "shot"
	},
  {
		"name": "War Chariot",//전차형기
		"unitType": "MachineGun",
	    "Range": 2,
		"movement": 2,
		"strength": 50,
		"rangedStrength": 5,
		"cost": 380,
		"requiredTech": "Dynamite",
	    "requiredResource": "Horses, Iron",
		"attackSound": "Machinegun"
	},
  	{
		"name": "Mechanized Infantry",//전차 중기
		"unitType": "MachineGun",
		"movement": 1,
		"strength": 50,
		"rangedStrength": 9,
		"Range": 3,
		"cost": 900,
		"requiredResource": "Horses, Iron:2",
		"requiredTech": "Dynamite",
		"attackSound": "Machinegun"
	},
  {
		"name": "Artillery",//155
		"unitType": "Canon",
		"movement": 1,
	    "movementCooldown":2,
		"strength": 90,
		"rangedStrength": 45,
		"range": 10,
		"cost": 4000,
	    "requiredResource": "Coal:2",
		"requiredTech": "Dynamite",
		"promotions": ["Indirect Fire"],
		"attackSound": "artillery"
	},
  {
		"name": "Cannon",//105
		"unitType": "Siege",
		"movement": 1,
	    "movementCooldown":1,
		"strength": 45,
		"rangedStrength": 22,
		"cost": 1830,
	    "Range": 5,
	    "requiredResource": "Coal",
		"requiredTech": "Dynamite",
		"attackSound": "cannon"
	},
  {
		"name": "Panzer",//105미리
		"unitType": "MovingCanon",
		"movement": 3,
	    "Range": 7,
		"strength": 70,
	    "rangedStrength":22,
		"cost": 4970,
	    "requiredResource": "Oil:2",
		"requiredTech": "Dynamite",
		"attackSound": "tankshot"
	},
  {
		"name": "Landship",//76미리
		"unitType": "MovingCanon",
		"movement": 5,
		"strength": 45,
	    "Range": 7,
	    "rangedStrength": 13,
		"cost": 1940,
	    "requiredResource": "Oil",
		"requiredTech": "Dynamite",
		"attackSound": "tankshot"
	},
  {
     	"name": "Anti-Tank Gun",//90대전차
		"unitType": "AntiCanon",
		"movement": 1,
	    "movementCooldown":1,
		"strength": 70,
	    "Range": 3,
	    "rangedStrength": 32,
		"cost": 1140,
	    "requiredResource": "Iron, Coal, Horses",
		"requiredTech": "Dynamite",
		"attackSound": "machinegun"
	},
  {
		"name": "Musketman",//76대전차
		"unitType": "AntiCanon",
		"movement": 1,
		"strength": 35,
	    "Range": 2,
	    "rangedStrength": 16,
	    "requiredResource": "Coal, Horses",
		"cost": 570,
		"requiredTech": "Dynamite",
		"attackSound": "shot"
	},
	{
		"name": "Tank",//소형
		"unitType": "Tank",
		"movement": 6,
		"strength": 30,
		"rangedStrength": 14,
		"Range": 3,
		"cost": 2860,
		"requiredResource":"Aluminum",
		"requiredTech": "Dynamite",
		"attackSound": "tankshot"
	},
  {
		"name": "Modern Armor",//전차
		"unitType": "Tank",
		"movement": 5,
		"strength": 120,
	    "Range": 4,
	    "rangedStrength": 30,
		"cost": 7430,
	    "requiredResource":"Aluminum:3",
		"requiredTech": "Dynamite",
		"attackSound": "tankshot"
	},
  {
		"name": "Fighter",//제트
		"unitType": "Flight",
		"movement": 8,
		"strength": 14,
		"rangedStrength": 45,
		"range": 2,
		"cost": 14300,
	    "requiredResource":"Oil:2, Aluminum",
		"requiredTech": "Dynamite",
		"attackSound": "machinegun"
	},
  {
		"name": "Bomber",//전폭
		"unitType": "Bomber",
		"movement": 6,
		"strength": 160,
		"rangedStrength": 175,
		"range": 0,
		"cost": 37150,
	    "requiredResource": "Oil:2, Aluminum:3",
		"requiredTech": "Dynamite",
		"attackSound": "bombing"
	},
  {
		"name": "Great War Bomber",//중폭
		"unitType": "Bomber",
		"movement": 7,
		"strength": 40,
		"rangedStrength": 95,
		"range": 0,
		"cost": 18800,
	    "requiredResource":"Oil, Aluminum:2",
		"requiredTech": "Dynamite",
		"attackSound": "bombing"
	},
  {
		"name": "Triplane",//그냥 전투기
		"unitType": "Fighter",
		"movement": 8,
		"strength": 12,
		"rangedStrength": 38,
		"range": 2,
		"cost": 4100,
	    "requiredResource":"Oil, Aluminum",
		"requiredTech": "Dynamite",
		"attackSound": "machinegun"
	}
]
